canvasautorubric/__init__.py
canvasautorubric/__main__.py
canvasautorubric/plot.py
canvasautorubric/utils.py
canvasautorubric-0.2.1.dist-info/AUTHORS
canvasautorubric-0.2.1.dist-info/METADATA
canvasautorubric-0.2.1.dist-info/WHEEL
canvasautorubric-0.2.1.dist-info/entry_points.txt
canvasautorubric-0.2.1.dist-info/pbr.json
canvasautorubric-0.2.1.dist-info/top_level.txt
canvasautorubric-0.2.1.dist-info/RECORD
