Metadata-Version: 2.1
Name: canvasautorubric
Version: 0.2.1
Summary: A tool automatically updating grades with rubric on canvas lms
Home-page: UNKNOWN
Author: tc-imba
Author-email: liuyh615@sjtu.edu.cn
License: Apache-2
Project-URL: Source Code, https://github.com/tc-imba/canvas-auto-rubric
Keywords: canvaslms
Platform: UNKNOWN
License-File: AUTHORS
Requires-Dist: canvasapi (==1.0.0)
Requires-Dist: click
Requires-Dist: pbr
Requires-Dist: logzero
Requires-Dist: scipy
Requires-Dist: pandas
Requires-Dist: openpyxl
Requires-Dist: matplotlib
Requires-Dist: enlighten
